{
    "name": "com.leinardi.gkraken",
    "build_sucess": true,
    "is_reproducible": false,
    "use_fixed_time": false,
    "commit": "7888065661d10cb738c3575db460c1c70b9a7873d18deec059587f561775a762",
    "branch": "stable",
    "time_of_rebuild": "2022-02-23 21:39:14+00:00",
    "timestamp_of_rebuild": 1645652354.0,
    "build_time": 483.749568939209,
    "cache_size": 112485330,
    "git_size": 7843596,
    "dl_size": 104636443,
    "bad_files": 53,
    "total_files": 3252,
    "repro_score": 0.9837023370233703,
    "original_hash": "ac1555d7369e087eec5afc1a8d3f51df2b7c48d1",
    "rebuild_hash": "c4c145ebbe206e5fee50e360adeb1a102b904ab7",
    "original_bin_hash": "c0c0bcc0b936df52aa0344c88ffb80c0020ebb6e",
    "rebuild_bin_hash": "e2da2ae755512638d2cce8df85de7f703fa1506a",
    "original_elf_hash": "b2017bec48821d8767ae0dfc5afe3748e386a92b",
    "rebuild_elf_hash": "fc0117f890d4987ab592ecc5caf4adac891d8df3",
    "is_bin_reproducible": false,
    "is_elf_reproducible": false,
    "diffoscope_failed": true
}